py_querybuilder/__init__.py
py_querybuilder/__version__.py
py_querybuilder/api.py
py_querybuilder-1.0.0.dist-info/LICENSE
py_querybuilder-1.0.0.dist-info/METADATA
py_querybuilder-1.0.0.dist-info/WHEEL
py_querybuilder-1.0.0.dist-info/top_level.txt
py_querybuilder-1.0.0.dist-info/RECORD
