Metadata-Version: 2.1
Name: py-querybuilder
Version: 1.0.0
Summary: Python Query Builder.
Home-page: https://github.com/tiagofernandez/py-querybuilder
Author: Tiago Fernandez
Author-email: tiago.fernandez@gmail.com
License: MIT
Keywords: python querybuilder sql
Platform: UNKNOWN
Classifier: License :: OSI Approved :: MIT License
Classifier: Programming Language :: Python :: 3.9
Requires-Python: >=3.9
Requires-Dist: jinjasql
Requires-Dist: sqlparse
